Workbook

Sheet Dashboard
A1: 📊 SALES PERFORMANCE DASHBOARD • 2023
B5: 💰 Total Revenue $12,638,329 | D5: 📈 Total Profit $2,550,680 | G5: 🏆 Top Product Laptop | I5: 📍 Top Region North
B9: Revenue by Region | G9: Revenue by Product
B28: Monthly Revenue Trend • Jan – Dec 2023

Sheet Raw Data
A1: Date | B1: Region | C1: Product | D1: Salesperson | E1: Units_Sold | F1: Unit_Price ($) | G1: Revenue ($) | H1: Profit ($) | I1: Profit Margin % | J1: Category
A2: 45138 | B2: South | C2: Tablet | D2: Charlie | E2: 2 | F2: 682 | G2: 1364 | H2: 393.0173 | I2: =IFERROR(H2/G2,0) -> 0.28813585 | J2: =IF(G2>=50000,"High",IF(G2>=20000,"Medium","Low")) -> Low
A3: 45046 | B3: South | C3: Tablet | D3: Bob | E3: 35 | F3: 1101 | G3: 38535 | H3: 5851.9001 | I3: =IFERROR(H3/G3,0) -> 0.15185935 | J3: =IF(G3>=50000,"High",IF(G3>=20000,"Medium","Low")) -> Medium
A4: 45260 | B4: South | C4: Laptop | D4: Eva | E4: 37 | F4: 1248 | G4: 46176 | H4: 8585.5666 | I4: =IFERROR(H4/G4,0) -> 0.18593136 | J4: =IF(G4>=50000,"High",IF(G4>=20000,"Medium","Low")) -> Medium
A5: 45169 | B5: West | C5: Tablet | D5: David | E5: 5 | F5: 1876 | G5: 9380 | H5: 2575.2419 | I5: =IFERROR(H5/G5,0) -> 0.27454605 | J5: =IF(G5>=50000,"High",IF(G5>=20000,"Medium","Low")) -> Low
A6: 45077 | B6: North | C6: Headphones | D6: David | E6: 1 | F6: 1340 | G6: 1340 | H6: 359.6382 | I6: =IFERROR(H6/G6,0) -> 0.26838671 | J6: =IF(G6>=50000,"High",IF(G6>=20000,"Medium","Low")) -> Low
A7: 45138 | B7: West | C7: Headphones | D7: Charlie | E7: 40 | F7: 681 | G7: 27240 | H7: 3737.8805 | I7: =IFERROR(H7/G7,0) -> 0.13722028 | J7: =IF(G7>=50000,"High",IF(G7>=20000,"Medium","Low")) -> Medium
A8: 45230 | B8: West | C8: Laptop | D8: Bob | E8: 12 | F8: 1615 | G8: 19380 | H8: 5049.0455 | I8: =IFERROR(H8/G8,0) -> 0.26052866 | J8: =IF(G8>=50000,"High",IF(G8>=20000,"Medium","Low")) -> Low
A9: 45016 | B9: South | C9: Tablet | D9: David | E9: 36 | F9: 1116 | G9: 40176 | H9: 7699.2233 | I9: =IFERROR(H9/G9,0) -> 0.19163738 | J9: =IF(G9>=50000,"High",IF(G9>=20000,"Medium","Low")) -> Medium
A10: 45138 | B10: South | C10: Tablet | D10: Charlie | E10: 45 | F10: 1193 | G10: 53685 | H10: 10554.137 | I10: =IFERROR(H10/G10,0) -> 0.19659377 | J10: =IF(G10>=50000,"High",IF(G10>=20000,"Medium","Low")) -> High
A11: 45260 | B11: West | C11: Tablet | D11: Eva | E11: 23 | F11: 1163 | G11: 26749 | H11: 3388.9912 | I11: =IFERROR(H11/G11,0) -> 0.12669599 | J11: =IF(G11>=50000,"High",IF(G11>=20000,"Medium","Low")) -> Medium
A12: 45260 | B12: North | C12: Smartwatch | D12: David | E12: 47 | F12: 736 | G12: 34592 | H12: 4016.8335 | I12: =IFERROR(H12/G12,0) -> 0.1161203 | J12: =IF(G12>=50000,"High",IF(G12>=20000,"Medium","Low")) -> Medium
A13: 45169 | B13: East | C13: Smartphone | D13: Charlie | E13: 31 | F13: 1302 | G13: 40362 | H13: 9912.4173 | I13: =IFERROR(H13/G13,0) -> 0.24558786 | J13: =IF(G13>=50000,"High",IF(G13>=20000,"Medium","Low")) -> Medium
... A501: 44957 | B501: West | C501: Tablet | D501: David | E501: 3 | F501: 762 | G501: 2286 | H501: 472.46437 | I501: =IFERROR(H501/G501,0) -> 0.20667733 | J501: =IF(G501>=50000,"High",IF(G501>=20000,"Medium","Low")) -> Low

Sheet Region Summary
A1: Region | B1: Revenue ($)
A2: North | B2: 3796463
A3: South | B3: 3101447
A4: West | B4: 2946136
A5: East | B5: 2794283

Sheet Analysis
A1: SALES ANALYSIS — KEY METRICS & FORMULAS
A3: Salesperson Performance
A4: Salesperson | B4: Total Revenue ($) | C4: # Orders | D4: Avg Order ($) | E4: Total Profit ($) | F4: Avg Margin %
A5: Alice | B5: =SUMIF('Raw Data'!D:D,A5,'Raw Data'!G:G) -> 2411532 | C5: =COUNTIF('Raw Data'!D:D,A5) -> 97 | D5: =AVERAGEIF('Raw Data'!D:D,A5,'Raw Data'!G:G) -> 24861.155 | E5: =SUMIF('Raw Data'!D:D,A5,'Raw Data'!H:H) -> 491239.38 | F5: =AVERAGEIF('Raw Data'!D:D,A5,'Raw Data'!I:I) -> 0.19904401
A6: Bob | B6: =SUMIF('Raw Data'!D:D,A6,'Raw Data'!G:G) -> 2338784 | C6: =COUNTIF('Raw Data'!D:D,A6) -> 104 | D6: =AVERAGEIF('Raw Data'!D:D,A6,'Raw Data'!G:G) -> 22488.308 | E6: =SUMIF('Raw Data'!D:D,A6,'Raw Data'!H:H) -> 464313.27 | F6: =AVERAGEIF('Raw Data'!D:D,A6,'Raw Data'!I:I) -> 0.196046
A7: Charlie | B7: =SUMIF('Raw Data'!D:D,A7,'Raw Data'!G:G) -> 2752939 | C7: =COUNTIF('Raw Data'!D:D,A7) -> 98 | D7: =AVERAGEIF('Raw Data'!D:D,A7,'Raw Data'!G:G) -> 28091.214 | E7: =SUMIF('Raw Data'!D:D,A7,'Raw Data'!H:H) -> 578936.09 | F7: =AVERAGEIF('Raw Data'!D:D,A7,'Raw Data'!I:I) -> 0.21096977
A8: David | B8: =SUMIF('Raw Data'!D:D,A8,'Raw Data'!G:G) -> 2387041 | C8: =COUNTIF('Raw Data'!D:D,A8) -> 99 | D8: =AVERAGEIF('Raw Data'!D:D,A8,'Raw Data'!G:G) -> 24111.525 | E8: =SUMIF('Raw Data'!D:D,A8,'Raw Data'!H:H) -> 471207.41 | F8: =AVERAGEIF('Raw Data'!D:D,A8,'Raw Data'!I:I) -> 0.20121855
A9: Eva | B9: =SUMIF('Raw Data'!D:D,A9,'Raw Data'!G:G) -> 2748033 | C9: =COUNTIF('Raw Data'!D:D,A9) -> 102 | D9: =AVERAGEIF('Raw Data'!D:D,A9,'Raw Data'!G:G) -> 26941.5 | E9: =SUMIF('Raw Data'!D:D,A9,'Raw Data'!H:H) -> 544984.12 | F9: =AVERAGEIF('Raw Data'!D:D,A9,'Raw Data'!I:I) -> 0.18941705
A10: TOTAL | B10: =SUM(B5:B9) -> 12638329 | C10: =SUM(C5:C9) -> 500 | D10: =AVERAGE(D5:D9) -> 25298.74 | E10: =SUM(E5:E9) -> 2550680.3 | F10: =AVERAGE(F5:F9) -> 0.19933907
A13: Revenue Matrix: Product × Region (SUMIFS)
A14: Product \ Region | B14: East | C14: North | D14: South | E14: West | F14: Row Total
A15: Headphones | B15: =SUMIFS('Raw Data'!G:G,'Raw Data'!C:C,A15,'Raw Data'!B:B,B14) -> 617820 | C15: =SUMIFS('Raw Data'!G:G,'Raw Data'!C:C,A15,'Raw Data'!B:B,C14) -> 568935 | D15: =SUMIFS('Raw Data'!G:G,'Raw Data'!C:C,A15,'Raw Data'!B:B,D14) -> 390522 | E15: =SUMIFS('Raw Data'!G:G,'Raw Data'!C:C,A15,'Raw Data'!B:B,E14) -> 511151 | F15: =SUM(B15:E15) -> 2088428
A16: Laptop | B16: =SUMIFS('Raw Data'!G:G,'Raw Data'!C:C,A16,'Raw Data'!B:B,B14) -> 431156 | C16: =SUMIFS('Raw Data'!G:G,'Raw Data'!C:C,A16,'Raw Data'!B:B,C14) -> 917306 | D16: =SUMIFS('Raw Data'!G:G,'Raw Data'!C:C,A16,'Raw Data'!B:B,D14) -> 759151 | E16: =SUMIFS('Raw Data'!G:G,'Raw Data'!C:C,A16,'Raw Data'!B:B,E14) -> 849229 | F16: =SUM(B16:E16) -> 2956842
A17: Smartphone | B17: =SUMIFS('Raw Data'!G:G,'Raw Data'!C:C,A17,'Raw Data'!B:B,B14) -> 649691 | C17: =SUMIFS('Raw Data'!G:G,'Raw Data'!C:C,A17,'Raw Data'!B:B,C14) -> 639494 | D17: =SUMIFS('Raw Data'!G:G,'Raw Data'!C:C,A17,'Raw Data'!B:B,D14) -> 441002 | E17: =SUMIFS('Raw Data'!G:G,'Raw Data'!C:C,A17,'Raw Data'!B:B,E14) -> 612853 | F17: =SUM(B17:E17) -> 2343040
A18: Smartwatch | B18: =SUMIFS('Raw Data'!G:G,'Raw Data'!C:C,A18,'Raw Data'!B:B,B14) -> 592071 | C18: =SUMIFS('Raw Data'!G:G,'Raw Data'!C:C,A18,'Raw Data'!B:B,C14) -> 818584 | D18: =SUMIFS('Raw Data'!G:G,'Raw Data'!C:C,A18,'Raw Data'!B:B,D14) -> 428141 | E18: =SUMIFS('Raw Data'!G:G,'Raw Data'!C:C,A18,'Raw Data'!B:B,E14) -> 538137 | F18: =SUM(B18:E18) -> 2376933
A19: Tablet | B19: =SUMIFS('Raw Data'!G:G,'Raw Data'!C:C,A19,'Raw Data'!B:B,B14) -> 503545 | C19: =SUMIFS('Raw Data'!G:G,'Raw Data'!C:C,A19,'Raw Data'!B:B,C14) -> 852144 | D19: =SUMIFS('Raw Data'!G:G,'Raw Data'!C:C,A19,'Raw Data'!B:B,D14) -> 1082631 | E19: =SUMIFS('Raw Data'!G:G,'Raw Data'!C:C,A19,'Raw Data'!B:B,E14) -> 434766 | F19: =SUM(B19:E19) -> 2873086

Sheet Monthly Summary
A1: Month | B1: Revenue ($)
A2: Jan-2023 | B2: 1253930
A3: Feb-2023 | B3: 901948
A4: Mar-2023 | B4: 1372699
A5: Apr-2023 | B5: 803163
A6: May-2023 | B6: 711639
A7: Jun-2023 | B7: 1065349
A8: Jul-2023 | B8: 1010735
A9: Aug-2023 | B9: 1127494
A10: Sep-2023 | B10: 955645
A11: Oct-2023 | B11: 1222006
A12: Nov-2023 | B12: 715954
A13: Dec-2023 | B13: 1497767

Sheet Product Summary
A1: Product | B1: Revenue ($)
A2: Laptop | B2: 2956842
A3: Tablet | B3: 2873086
A4: Smartwatch | B4: 2376933
A5: Smartphone | B5: 2343040
A6: Headphones | B6: 2088428
